translator/__init__.py
translator/translator.py
hc_translator-0.1.dist-info/METADATA
hc_translator-0.1.dist-info/WHEEL
hc_translator-0.1.dist-info/top_level.txt
hc_translator-0.1.dist-info/RECORD
